pytest_smtp/__init__.py
pytest_smtp/email_template.py
pytest_smtp/plugin.py
pytest_smtp-0.1.dist-info/LICENSE
pytest_smtp-0.1.dist-info/METADATA
pytest_smtp-0.1.dist-info/WHEEL
pytest_smtp-0.1.dist-info/entry_points.txt
pytest_smtp-0.1.dist-info/top_level.txt
pytest_smtp-0.1.dist-info/zip-safe
pytest_smtp-0.1.dist-info/RECORD
